comparable/__init__.py
comparable/base.py
comparable/compound.py
comparable/simple.py
comparable/tools.py
comparable/test/__init__.py
comparable/test/settings.py
comparable/test/test_base.py
comparable/test/test_compound.py
comparable/test/test_simple.py
comparable/test/test_tools.py
Comparable-1.0.dist-info/DESCRIPTION.rst
Comparable-1.0.dist-info/entry_points.txt
Comparable-1.0.dist-info/METADATA
Comparable-1.0.dist-info/metadata.json
Comparable-1.0.dist-info/RECORD
Comparable-1.0.dist-info/top_level.txt
Comparable-1.0.dist-info/WHEEL
