Metadata-Version: 2.0
Name: Comparable
Version: 1.0
Summary: Base class to enable objects to be compared for similarity.
Home-page: https://github.com/jacebrowning/comparable
Author: Jace Browning
Author-email: jacebrowning@gmail.com
License: LGPL
Platform: UNKNOWN
Classifier: Development Status :: 4 - Beta
Classifier: Intended Audience :: Developers
Classifier: License :: OSI Approved :: GNU Lesser General Public License v3 (LGPLv3)
Classifier: Natural Language :: English
Classifier: Operating System :: OS Independent
Classifier: Programming Language :: Python :: 3
Classifier: Programming Language :: Python :: 3.3
Classifier: Topic :: Software Development :: Libraries
